azure/mgmt/timeseriesinsights/__init__.py
azure/mgmt/timeseriesinsights/_configuration.py
azure/mgmt/timeseriesinsights/_time_series_insights_client.py
azure/mgmt/timeseriesinsights/_version.py
azure/mgmt/timeseriesinsights/aio/__init__.py
azure/mgmt/timeseriesinsights/aio/_configuration.py
azure/mgmt/timeseriesinsights/aio/_time_series_insights_client.py
azure/mgmt/timeseriesinsights/aio/operations/__init__.py
azure/mgmt/timeseriesinsights/aio/operations/_access_policies_operations.py
azure/mgmt/timeseriesinsights/aio/operations/_environments_operations.py
azure/mgmt/timeseriesinsights/aio/operations/_event_sources_operations.py
azure/mgmt/timeseriesinsights/aio/operations/_operations.py
azure/mgmt/timeseriesinsights/aio/operations/_reference_data_sets_operations.py
azure/mgmt/timeseriesinsights/models/__init__.py
azure/mgmt/timeseriesinsights/models/_models.py
azure/mgmt/timeseriesinsights/models/_models_py3.py
azure/mgmt/timeseriesinsights/models/_time_series_insights_client_enums.py
azure/mgmt/timeseriesinsights/operations/__init__.py
azure/mgmt/timeseriesinsights/operations/_access_policies_operations.py
azure/mgmt/timeseriesinsights/operations/_environments_operations.py
azure/mgmt/timeseriesinsights/operations/_event_sources_operations.py
azure/mgmt/timeseriesinsights/operations/_operations.py
azure/mgmt/timeseriesinsights/operations/_reference_data_sets_operations.py
azure_mgmt_timeseriesinsights-1.0.0.dist-info/METADATA
azure_mgmt_timeseriesinsights-1.0.0.dist-info/WHEEL
azure_mgmt_timeseriesinsights-1.0.0.dist-info/top_level.txt
azure_mgmt_timeseriesinsights-1.0.0.dist-info/RECORD
